[
    {
        "max": 29,
        "min": 89
    },
    {
        "max": 19,
        "min": 24
    },
    {
        "max": 82,
        "min": 47
    },
    {
        "max": 26,
        "min": 83
    },
    {
        "max": 12,
        "min": 69
    },
    {
        "max": 10,
        "min": 42
    },
    {
        "max": 29,
        "min": 74
    },
    {
        "max": 82,
        "min": 89
    },
    {
        "max": 41,
        "min": 62
    },
    {
        "max": 23,
        "min": 17
    },
    {
        "max": 13,
        "min": 10
    },
    {
        "max": 76,
        "min": 33
    },
    {
        "max": 77,
        "min": 43
    },
    {
        "max": 83,
        "min": 12
    },
    {
        "max": 15,
        "min": 73
    },
    {
        "max": 12,
        "min": 89
    },
    {
        "max": 57,
        "min": 88
    },
    {
        "max": 45,
        "min": 63
    },
    {
        "max": 49,
        "min": 45
    },
    {
        "max": 88,
        "min": 47
    },
    {
        "max": 79,
        "min": 10
    },
    {
        "max": 77,
        "min": 13
    },
    {
        "max": 14,
        "min": 67
    },
    {
        "max": 31,
        "min": 65
    },
    {
        "max": 15,
        "min": 47
    },
    {
        "max": 64,
        "min": 75
    },
    {
        "max": 15,
        "min": 21
    },
    {
        "max": 49,
        "min": 44
    },
    {
        "max": 47,
        "min": 46
    },
    {
        "max": 78,
        "min": 34
    },
    {
        "max": 89,
        "min": 58
    },
    {
        "max": 85,
        "min": 13
    },
    {
        "max": 30,
        "min": 88
    },
    {
        "max": 26,
        "min": 60
    },
    {
        "max": 56,
        "min": 72
    },
    {
        "max": 45,
        "min": 48
    },
    {
        "max": 50,
        "min": 42
    },
    {
        "max": 67,
        "min": 22
    },
    {
        "max": 88,
        "min": 53
    },
    {
        "max": 88,
        "min": 23
    },
    {
        "max": 31,
        "min": 90
    },
    {
        "max": 28,
        "min": 68
    },
    {
        "max": 57,
        "min": 84
    },
    {
        "max": 14,
        "min": 29
    },
    {
        "max": 21,
        "min": 35
    },
    {
        "max": 36,
        "min": 27
    },
    {
        "max": 59,
        "min": 58
    },
    {
        "max": 67,
        "min": 26
    },
    {
        "max": 55,
        "min": 15
    },
    {
        "max": 84,
        "min": 14
    },
    {
        "max": 76,
        "min": 13
    },
    {
        "max": 25,
        "min": 60
    },
    {
        "max": 72,
        "min": 81
    },
    {
        "max": 73,
        "min": 61
    },
    {
        "max": 89,
        "min": 21
    }
]